drewsTools/__init__.py
drewsTools/l0/__init__.py
drewsTools/l0/functions.py
drewsTools/l0/proxmox.py
drewsTools/l1/__init__.py
drewsTools/l1/proxmoxFunctions.py
drewsTools_drew9781-0.0.1.dist-info/METADATA
drewsTools_drew9781-0.0.1.dist-info/WHEEL
drewsTools_drew9781-0.0.1.dist-info/top_level.txt
drewsTools_drew9781-0.0.1.dist-info/RECORD
