Metadata-Version: 2.1
Name: drewsTools-drew9781
Version: 0.0.1
Summary: Reusable code for automation
Home-page: https://gitlab.com/drew9781/drewsTools
Author: Andrew Engleman
Author-email: drew9781@yahoo.com
License: UNKNOWN
Project-URL: Bug Tracker, https://gitlab.com/drew9781/drewsTools/issues
Platform: UNKNOWN
Classifier: Programming Language :: Python :: 3
Classifier: License :: OSI Approved :: MIT License
Classifier: Operating System :: OS Independent
Requires-Python: >=3.6
